F:\PlanF\easyUtils\target\classes\com\com.yuan\util\local>javap -c Look.class
Compiled from "Look.java"
public class com.com.yuan.util.local.Look {
  public com.com.yuan.util.local.Look();
    Code:
       0: aload_0
       1: invokespecial #1                  // Method java/lang/Object."<init>":()V
       4: return

  public static void main(java.lang.String[]);
    Code:
    //将int类型值存入局部变量1
       0: iconst_1
    //将int类型值存入局部变量1
       1: istore_1
    //把一个常量值加到一个int类型的局部变量上
       2: iinc          1, 1
    //从类中获取静态字段
       5: getstatic     #2                  // Field java/lang/System.out:Ljava/io/PrintStream;
    //从局部变量1中装载int类型值
       8: iload_1
    //调度对象的实便方法
       9: invokevirtual #3                  // Method java/io/PrintStream.println:(I)V
    //把一个常量值加到一个int类型的局部变量上
      12: iinc          1, 1
    //
      15: return


    
}
